{
  "data":[
    {"name":"Cherry Willow",
      "url":"http://cherrywillow.com",
      "git_repo":{
        "url":"",
        "git":"https://Guamaso@bitbucket.org/Guamaso/cherry-willow.git"
      },
      "webhost":{
        "name":"Digital Ocean",
        "url":"http://digitalocean.com",
        "server_name":"EGS_WEB",
        "project_id":"CW",
        "parent_id":"SW"
      },
      "domain_registrar":{
        "name":"Hover",
        "url": "https://hover.com",
        "expire_date": "09/13/2015",
        "fee":"15.00"
      },
      "cms":{
        "name":"Ghost",
        "version":"5.0"
      },
      "email":{
        "served_by":"Hover",
        "cost":"5.00"
      }
    },
    {"name":"Juan Orozco",
      "url":"http://juanorozco.com",
      "git_repo":{
        "url":"https://github.com/Guamaso/juanorozco-com",
        "git":"https://github.com/Guamaso/juanorozco-com.git"
      },
      "webhost":{
        "name":"Github Pages",
        "url":"http://pages.github.com"
      },
      "domain_registrar":{
        "name":"Hover",
        "url": "https://hover.com",
        "expire_date": "03/22/2015",
        "fee":"15.00"
      },
      "cms":{
        "name":"Hand Built",
        "version":"1.0"
      }
    }
  ]
}
